hello_jupyter_proxy.py
hello_jupyter_proxy-0.2.dist-info/entry_points.txt
hello_jupyter_proxy-0.2.dist-info/LICENSE
hello_jupyter_proxy-0.2.dist-info/WHEEL
hello_jupyter_proxy-0.2.dist-info/METADATA
hello_jupyter_proxy-0.2.dist-info/RECORD
