Metadata-Version: 2.1
Name: hello_jupyter_proxy
Version: 0.2
Summary: A minimal example server to run with jupyter-server-proxy
Author-email: Thomas Kluyver <thomas@kluyver.me.uk>
Classifier: License :: OSI Approved :: MIT License
Requires-Dist: jupyter-server-proxy >=4.0
Project-URL: Home, https://github.com/takluyver/hello_jupyter_proxy
